pyfac.py
pyfac-1.0.0.dist-info/top_level.txt
pyfac-1.0.0.dist-info/WHEEL
pyfac-1.0.0.dist-info/metadata.json
pyfac-1.0.0.dist-info/METADATA
pyfac-1.0.0.dist-info/RECORD
pyfac-1.0.0.dist-info/DESCRIPTION.rst
