Metadata-Version: 2.0
Name: pyfac
Version: 1.0.0
Summary: Module and command-line utility for factoring integers
Home-page: https://pypi.python.org/pypi/pyfac
Author: lucasbrown.cit
Author-email: lucasbrown.cit@gmail.com
License: MIT
Keywords: integer factoring factorization primes prime numbers math mathematics
Platform: UNKNOWN
Classifier: Development Status :: 5 - Production/Stable
Classifier: Environment :: Console
Classifier: Intended Audience :: Education
Classifier: Intended Audience :: Science/Research
Classifier: License :: OSI Approved :: MIT License
Classifier: Programming Language :: Python
Classifier: Programming Language :: Python :: 2
Classifier: Programming Language :: Python :: 2.7
Classifier: Topic :: Scientific/Engineering
Classifier: Topic :: Scientific/Engineering :: Mathematics
Classifier: Topic :: Software Development :: Libraries
Classifier: Topic :: Utilities
